<?xml version="1.0" encoding="utf-8"?>      
<openerp>       
    <data noupdate="0">     

        <record id="base.hl7v3" model="res.partner">  
            <field name="name">HL7 v3</field>
            <field name="company_type">company</field>
            <field name="website">www.hl7.org</field>
            <field name="notify_email">none</field>
            <field name="category_id" eval="[(6, 0, [ref('hc_base.partner_source'), ref('hc_base.partner_document')])]"/>
            <field name="country_id" ref="base.us"/>
        </record>

        <record id="base.hl7v2" model="res.partner">  
            <field name="name">HL7 v2</field>
            <field name="company_type">company</field>
            <field name="website">www.hl7.org</field>
            <field name="notify_email">none</field>
            <field name="category_id" eval="[(6, 0, [ref('hc_base.partner_source'), ref('hc_base.partner_document')])]"/>
            <field name="country_id" ref="base.us"/>
        </record>

        <record id="base.hl7fhir" model="res.partner">  
            <field name="name">HL7 FHIR</field>
            <field name="company_type">company</field>
            <field name="website">www.hl7.org</field>
            <field name="notify_email">none</field>
            <field name="category_id" eval="[(6, 0, [ref('hc_base.partner_source'), ref('hc_base.partner_document')])]"/>
            <field name="country_id" ref="base.us"/>
        </record>

        <record id="base.snomed" model="res.partner">  
            <field name="name">SNOMED CT</field>
            <field name="company_type">company</field>
            <field name="website">www.ihtsdo.org/snomed-ct</field>
            <field name="notify_email">none</field>
            <field name="category_id" eval="[(6, 0, [ref('hc_base.partner_source'), ref('hc_base.partner_organization')])]"/>
            <field name="country_id" ref="base.dk"/>
        </record>

        <record id="base.nlm_rxnorm" model="res.partner">  
            <field name="name">RxNorm</field>
            <field name="company_type">company</field>
            <field name="website">https://www.nlm.nih.gov/research/umls/rxnorm/overview.html</field>
            <field name="notify_email">none</field>
            <field name="category_id" eval="[(6, 0, [ref('hc_base.partner_source'), ref('hc_base.partner_document')])]"/>
            <field name="country_id" ref="base.us"/>
        </record>

        <record id="base.nucc" model="res.partner">  
            <field name="name">National Uniform Claim Committee (NUCC)</field>
            <field name="company_type">company</field>
            <field name="website">https://www.nucc.org</field>
            <field name="commment">A standards organization in the United States that maintains code set for provider taxonomy.

                The National Uniform Claim Committee (NUCC) is a voluntary organization that develops a standardized data set for use by the non-institutional health care community to transmit claim and encounter information to and from all third-party payers. It is chaired by the American Medical Association (AMA), with the Centers for Medicare and Medicaid Services (CMS) as a critical partner. The committee includes representation from key provider and payer organizations, as well as designated standards maintenance organizations, public health organizations, and a vendor. (Ref: HIMMS http://www.himss.org/library/medical-banking/financial-systems/uniform-claims)</field>
            <field name="notify_email">none</field>
            <field name="category_id" eval="[(6, 0, [ref('hc_base.partner_source'), ref('hc_base.partner_organization')])]"/>
            <field name="country_id" ref="base.us"/>
        </record>
    </data>
</openerp>

